Codi/__init__.py
Codi/main.py
codi_api-0.1.0.dist-info/LICENSE
codi_api-0.1.0.dist-info/METADATA
codi_api-0.1.0.dist-info/WHEEL
codi_api-0.1.0.dist-info/top_level.txt
codi_api-0.1.0.dist-info/RECORD
