Metadata-Version: 2.1
Name: codi-api
Version: 0.1.0
Summary: A python package
Author-email: KnowingXR <knowing@mailfence.com>
Project-URL: Homepage, https://github.com/Boxei/Codi
Project-URL: Bug Tracker, https://github.com/Boxei/Codi/issues
Classifier: Programming Language :: Python :: 3
Classifier: License :: OSI Approved :: MIT License
Classifier: Operating System :: OS Independent
Requires-Python: >=3.7
License-File: LICENSE
